project_root_finder/__init__.py
project_root_finder-1.9.dist-info/licenses/LICENSE
project_root_finder-1.9.dist-info/METADATA
project_root_finder-1.9.dist-info/WHEEL
project_root_finder-1.9.dist-info/top_level.txt
project_root_finder-1.9.dist-info/RECORD
